README.rst
setup.py
./LICENSE
./__init__.py
./__main__.py
./develop.py
./hgignore.py
./readme.py
./revertablefile.py
./toxini.py
./ununinit.py
develop.egg-info/PKG-INFO
develop.egg-info/SOURCES.txt
develop.egg-info/dependency_links.txt
develop.egg-info/entry_points.txt
develop.egg-info/namespace_packages.txt
develop.egg-info/requires.txt
develop.egg-info/top_level.txt