Metadata-Version: 1.1
Name: develop
Version: 0.1.4
Summary: tool to develop python packages
Home-page: https://bitbucket.org/ruamel/develop
Author: Anthon van der Neut
Author-email: a.van.der.neut@ruamel.eu
License: MIT
Platform: UNKNOWN
Classifier: Development Status :: 4 - Beta
Classifier: Intended Audience :: Developers
Classifier: License :: OSI Approved :: MIT License
Classifier: Operating System :: OS Independent
Classifier: Programming Language :: Python
